hedger/__init__.py
hedger/util.py
hedger/scrap/__init__.py
hedger/scrap/web_results_search.py
hedger-0.0.4.dist-info/LICENSE
hedger-0.0.4.dist-info/METADATA
hedger-0.0.4.dist-info/WHEEL
hedger-0.0.4.dist-info/top_level.txt
hedger-0.0.4.dist-info/RECORD
