Metadata-Version: 2.1
Name: hedger
Version: 0.0.4
Summary: Semantic Finance
Home-page: https://github.com/thorwhalen/hedger
Author: Thor Whalen
License: apache-2.0
Keywords: finance,natural language processing,NLP,transformers
Platform: any
Requires-Dist: guise
Requires-Dist: importlib-resources
